mkdocstrings_handlers/vba/__init__.py
mkdocstrings_handlers/vba/_crossref.py
mkdocstrings_handlers/vba/_handler.py
mkdocstrings_handlers/vba/_regex.py
mkdocstrings_handlers/vba/_sort.py
mkdocstrings_handlers/vba/_types.py
mkdocstrings_handlers/vba/_util.py
mkdocstrings_handlers/vba/py.typed
mkdocstrings_handlers/vba/version.py
mkdocstrings_handlers/vba/templates/material/attribute.html
mkdocstrings_handlers/vba/templates/material/children.html
mkdocstrings_handlers/vba/templates/material/class.html
mkdocstrings_handlers/vba/templates/material/docstring.html
mkdocstrings_handlers/vba/templates/material/expression.html
mkdocstrings_handlers/vba/templates/material/labels.html
mkdocstrings_handlers/vba/templates/material/module.html
mkdocstrings_handlers/vba/templates/material/procedure.html
mkdocstrings_handlers/vba/templates/material/signature.html
mkdocstrings_handlers/vba/templates/material/style.css
mkdocstrings_handlers/vba/templates/material/_base/attribute.html
mkdocstrings_handlers/vba/templates/material/_base/children.html
mkdocstrings_handlers/vba/templates/material/_base/class.html
mkdocstrings_handlers/vba/templates/material/_base/docstring.html
mkdocstrings_handlers/vba/templates/material/_base/expression.html
mkdocstrings_handlers/vba/templates/material/_base/labels.html
mkdocstrings_handlers/vba/templates/material/_base/module.html
mkdocstrings_handlers/vba/templates/material/_base/procedure.html
mkdocstrings_handlers/vba/templates/material/_base/signature.html
mkdocstrings_handlers/vba/templates/material/_base/docstring/admonition.html
mkdocstrings_handlers/vba/templates/material/_base/docstring/attributes.html
mkdocstrings_handlers/vba/templates/material/_base/docstring/examples.html
mkdocstrings_handlers/vba/templates/material/_base/docstring/other_parameters.html
mkdocstrings_handlers/vba/templates/material/_base/docstring/parameters.html
mkdocstrings_handlers/vba/templates/material/_base/docstring/raises.html
mkdocstrings_vba-0.0.10.dist-info/LICENSE
mkdocstrings_vba-0.0.10.dist-info/METADATA
mkdocstrings_vba-0.0.10.dist-info/WHEEL
mkdocstrings_vba-0.0.10.dist-info/top_level.txt
mkdocstrings_vba-0.0.10.dist-info/RECORD
