Metadata-Version: 2.1
Name: mkdocstrings-vba
Version: 0.0.10
Summary: MkDocstrings VBA handler
Home-page: https://github.com/AutoActuary/mkdocstrings-vba
Author: Rudolf Byker
Author-email: rudolfbyker@gmail.com
Classifier: Programming Language :: Python :: 3
Classifier: License :: Other/Proprietary License
Classifier: Operating System :: OS Independent
Requires-Python: >=3.7
License-File: LICENSE
Requires-Dist: mkdocstrings <1,>=0.26.1
Requires-Dist: griffe <2,>=1.3.1
Requires-Dist: mkdocs-material <10,>=9.2
